slb_glossary_finder/__init__.py
slb_glossary_finder/exceptions.py
slb_glossary_finder/finder.py
slb_glossary_finder/save.py
slb_glossary_finder-0.1.0.dist-info/LICENSE
slb_glossary_finder-0.1.0.dist-info/METADATA
slb_glossary_finder-0.1.0.dist-info/WHEEL
slb_glossary_finder-0.1.0.dist-info/top_level.txt
slb_glossary_finder-0.1.0.dist-info/RECORD
