Metadata-Version: 2.1
Name: slb-glossary-finder
Version: 0.1.0
Summary: Finds and saves terms on the Schlumberger Oilfield Glossary website.
Author-email: "Daniel T. Afolayan (ti-oluwa)" <tioluwa.dev@gmail.com>
Maintainer-email: "Daniel T. Afolayan (ti-oluwa)" <tioluwa.dev@gmail.com>
Project-URL: Homepage, https://github.com/ti-oluwa/slb_glossary_finder
Project-URL: Bug Tracker, https://github.com/ti-oluwa/slb_glossary_finder/issues
Project-URL: Repository, https://github.com/ti-oluwa/slb_glossary_finder
Keywords: Schlumberger,Oilfield,Glossary,Petroleum terms,Petroleum
Classifier: Programming Language :: Python :: 3
Classifier: License :: OSI Approved :: MIT License
Classifier: Operating System :: OS Independent
Classifier: Development Status :: 3 - Alpha
Classifier: Environment :: Console
Requires-Python: >=3.7
License-File: LICENSE
Requires-Dist: selenium (>=4.10.0)
Requires-Dist: openpyxl (>=3.1.2)
